odoo/addons/ssi_l10n_id_taxform_bukti_potong_pph_f113301_work_log/README.rst
odoo/addons/ssi_l10n_id_taxform_bukti_potong_pph_f113301_work_log/__init__.py
odoo/addons/ssi_l10n_id_taxform_bukti_potong_pph_f113301_work_log/__manifest__.py
odoo/addons/ssi_l10n_id_taxform_bukti_potong_pph_f113301_work_log/models/__init__.py
odoo/addons/ssi_l10n_id_taxform_bukti_potong_pph_f113301_work_log/models/bukti_potong_pph_f113301_out.py
odoo/addons/ssi_l10n_id_taxform_bukti_potong_pph_f113301_work_log/static/description/icon.png
odoo14_addon_ssi_l10n_id_taxform_bukti_potong_pph_f113301_work_log-14.0.1.0.0.dist-info/METADATA
odoo14_addon_ssi_l10n_id_taxform_bukti_potong_pph_f113301_work_log-14.0.1.0.0.dist-info/WHEEL
odoo14_addon_ssi_l10n_id_taxform_bukti_potong_pph_f113301_work_log-14.0.1.0.0.dist-info/top_level.txt
odoo14_addon_ssi_l10n_id_taxform_bukti_potong_pph_f113301_work_log-14.0.1.0.0.dist-info/RECORD
